pdf_to_duc/__init__.py
pdf_to_duc/main.py
pdf_to_duc-1.0.1.dist-info/LICENSE
pdf_to_duc-1.0.1.dist-info/METADATA
pdf_to_duc-1.0.1.dist-info/WHEEL
pdf_to_duc-1.0.1.dist-info/top_level.txt
pdf_to_duc-1.0.1.dist-info/RECORD
